curious_machine/__init__.py
curious_machine/githf.py
curious_machine/machina.yaml
curious_machine-0.0.1.dist-info/licenses/LICENSE
curious_machine-0.0.1.dist-info/METADATA
curious_machine-0.0.1.dist-info/WHEEL
curious_machine-0.0.1.dist-info/top_level.txt
curious_machine-0.0.1.dist-info/RECORD
